pyrpm/__init__.py
pyrpm/spec.py
python_rpm_spec-0.16.0.dist-info/LICENSE
python_rpm_spec-0.16.0.dist-info/WHEEL
python_rpm_spec-0.16.0.dist-info/METADATA
python_rpm_spec-0.16.0.dist-info/RECORD
