Metadata-Version: 2.3
Name: python-rpm-spec
Version: 0.16.0
Summary: python-rpm-spec is a Python library for parsing RPM spec files.
Home-page: https://github.com/bkircher/python-rpm-spec
Author: Ben Kircher
Author-email: bkircher@0xadd.de
Requires-Python: >=3.9
